[
  {
    "symbol": "RELIANCE",
    "overall_signal": "neutral",
    "confidence": 0.25,
    "risk_level": "High",
    "recommendation": "Wait for better signals",
    "consensus_trend": "neutral",
    "signal_strength": 0.5,
    "supporting_timeframes": 3,
    "conflicting_timeframes": 3,
    "divergence_detected": false,
    "analysis_duration": 6.746764,
    "timeframes_analyzed": 6
  },
  {
    "symbol": "TCS",
    "overall_signal": "bearish",
    "confidence": 0.17592592592592593,
    "risk_level": "High",
    "recommendation": "Wait for better signals",
    "consensus_trend": "bearish",
    "signal_strength": 0.5277777777777778,
    "supporting_timeframes": 2,
    "conflicting_timeframes": 2,
    "divergence_detected": false,
    "analysis_duration": 6.696927,
    "timeframes_analyzed": 6
  },
  {
    "symbol": "HDFCBANK",
    "overall_signal": "bullish",
    "confidence": 0.3949416342412451,
    "risk_level": "High",
    "recommendation": "Wait for confirmation - divergence detected",
    "consensus_trend": "bullish",
    "signal_strength": 0.7898832684824902,
    "supporting_timeframes": 3,
    "conflicting_timeframes": 3,
    "divergence_detected": true,
    "analysis_duration": 6.737144,
    "timeframes_analyzed": 6
  },
  {
    "symbol": "INFY",
    "overall_signal": "bullish",
    "confidence": 0.3172205438066465,
    "risk_level": "High",
    "recommendation": "Wait for better signals",
    "consensus_trend": "bullish",
    "signal_strength": 0.634441087613293,
    "supporting_timeframes": 3,
    "conflicting_timeframes": 3,
    "divergence_detected": false,
    "analysis_duration": 6.737648,
    "timeframes_analyzed": 6
  },
  {
    "symbol": "ICICIBANK",
    "overall_signal": "bullish",
    "confidence": 0.18437118437118438,
    "risk_level": "High",
    "recommendation": "Wait for better signals",
    "consensus_trend": "bullish",
    "signal_strength": 0.5531135531135531,
    "supporting_timeframes": 2,
    "conflicting_timeframes": 1,
    "divergence_detected": false,
    "analysis_duration": 6.729301,
    "timeframes_analyzed": 6
  }
]